VERILOG/dff.v
module dff(
    input wire clk,
    input wire rst,  
    input wire d,
    output reg q
);
    always @(posedge clk) begin
        if (rst)
            q <= 1'b1;
        else
            q <= d;
    end
    
endmodule

VERILOG/cla_adder.v
`include "dff.v"
module cla_adder (
    input wire clk,
    input wire [4:0] a,
    input wire [4:0] b,
    output wire [4:0] sum,
    output wire cout
);
    wire [4:0] qa, qb;
    wire [4:0] s;
    wire qc0;
    wire [4:0] gb;
    wire [4:0] p, g;
    wire [4:0] c;
    wire [14:0] w;
    
    assign c[0]=0;
    
    dff qa0 (.clk(clk), .d(a[0]), .q(qa[0]));
    dff qa1 (.clk(clk), .d(a[1]), .q(qa[1]));
    dff qa2 (.clk(clk), .d(a[2]), .q(qa[2]));
    dff qa3 (.clk(clk), .d(a[3]), .q(qa[3]));
    dff qa4 (.clk(clk), .d(a[4]), .q(qa[4]));
    
    dff qb0 (.clk(clk), .d(b[0]), .q(qb[0]));
    dff qb1 (.clk(clk), .d(b[1]), .q(qb[1]));
    dff qb2 (.clk(clk), .d(b[2]), .q(qb[2]));
    dff qb3 (.clk(clk), .d(b[3]), .q(qb[3]));
    dff qb4 (.clk(clk), .d(b[4]), .q(qb[4]));
    
    dff qcin (.clk(clk), .d(c[0]), .q(qc0));
    
    //Pi and Gi generator

    xor (p[0],qa[0],qb[0]);
    xor (p[1],qa[1],qb[1]);
    xor (p[2],qa[2],qb[2]);
    xor (p[3],qa[3],qb[3]);
    xor (p[4],qa[4],qb[4]);
    
    nand (gb[0],qa[0],qb[0]);
    nand (gb[1],qa[1],qb[1]);
    nand (gb[2],qa[2],qb[2]);
    nand (gb[3],qa[3],qb[3]);
    nand (gb[4],qa[4],qb[4]);  
    
    assign g[0]=~gb[0];
    assign g[1]=~gb[1];
    assign g[2]=~gb[2];
    assign g[3]=~gb[3];
    assign g[4]=~gb[4];
    
    // Carry Generator
    //C1
    nand(w[0],p[0],g[0]);
    nand(c[1],w[0],gb[0]);
    //C2
    nand(w[1],p[1],g[0]);
    nand(w[2],p[1],p[0],c[0]);
    nand(c[2],w[1],w[2],gb[1]);
    //C3
    nand(w[3],p[2],g[1]);
    nand(w[4],p[2],p[1],g[0]);
    nand(w[5],p[2],p[1],p[0],c[0]);
    nand(c[3],w[3],w[4],w[5],gb[2]);
    //C4
    nand(w[6],p[3],g[2]);
    nand(w[7],p[3],p[2],g[1]);
    nand(w[8],p[3],p[2],p[1],g[0]);
    nand(w[9],p[3],p[2],p[1],p[0],c[0]);
    nand(c[4],w[6],w[7],w[8],w[9],gb[3]);
    //Cout
    nand(w[10],p[4],g[3]);
    nand(w[11],p[4],p[3],g[2]);
    nand(w[12],p[4],p[3],p[2],g[1]);
    nand(w[13],p[4],p[3],p[2],p[1],g[0]);
    nand(w[14],p[4],p[3],p[2],p[1],p[0],c[0]);
    nand(cout,w[10],w[11],w[12],w[13],w[14],gb[4]);
    
    //SUM
    xor(s[0],p[0],c[0]);
    xor(s[1],p[1],c[1]);
    xor(s[2],p[2],c[2]);
    xor(s[3],p[3],c[3]);
    xor(s[4],p[4],c[4]);
    
    dff qsum0 (.clk(clk), .d(s[0]), .q(sum[0]));
    dff qsum1 (.clk(clk), .d(s[1]), .q(sum[1]));
    dff qsum2 (.clk(clk), .d(s[2]), .q(sum[2]));
    dff qsum3 (.clk(clk), .d(s[3]), .q(sum[3]));
    dff qsum4 (.clk(clk), .d(s[4]), .q(sum[4]));
    
endmodule

VERILOG/cla_adder_tb.v
module cla_adder_tb;
    reg clk;
    reg [4:0] a, b;
    wire [4:0] sum;
    wire cout;
    
    cla_adder uut (
        .clk(clk),
        .a(a),
        .b(b),
        .sum(sum),
        .cout(cout)
    );

    initial begin
        clk = 0;
        forever #50 clk = ~clk;
    end
    
    initial begin
        $dumpfile("cla_adder_test.vcd");
        $dumpvars(0, cla_adder_tb);
   
        a = 0;
        b = 0;
        #100;

        a = 5'b00001; b = 5'b00001; 
        #100;

        a = 5'b11111; b = 5'b00001;
        #100;

        a = 5'b10101; b = 5'b01101; 
        #100;

        a = 5'b00010; b = 5'b11011; 
        #100;

        a = 5'b11111; b = 5'b11111; 
        #100;
        
        #100;
        
        $finish;
    end
endmodule

VERILOG/cla_adder_test.vcd
$date
	Wed Dec  3 05:07:47 2025
$end
$version
	Icarus Verilog
$end
$timescale
	1s
$end
$scope module cla_adder_tb $end
$var wire 5 ! sum [4:0] $end
$var wire 1 " cout $end
$var reg 5 # a [4:0] $end
$var reg 5 $ b [4:0] $end
$var reg 1 % clk $end
$scope module uut $end
$var wire 5 & a [4:0] $end
$var wire 5 ' b [4:0] $end
$var wire 1 % clk $end
$var wire 1 " cout $end
$var wire 15 ( w [14:0] $end
$var wire 5 ) sum [4:0] $end
$var wire 5 * s [4:0] $end
$var wire 1 + qc0 $end
$var wire 5 , qb [4:0] $end
$var wire 5 - qa [4:0] $end
$var wire 5 . p [4:0] $end
$var wire 5 / gb [4:0] $end
$var wire 5 0 g [4:0] $end
$var wire 5 1 c [4:0] $end
$scope module qa0 $end
$var wire 1 % clk $end
$var wire 1 2 d $end
$var wire 1 3 rst $end
$var reg 1 4 q $end
$upscope $end
$scope module qa1 $end
$var wire 1 % clk $end
$var wire 1 5 d $end
$var wire 1 6 rst $end
$var reg 1 7 q $end
$upscope $end
$scope module qa2 $end
$var wire 1 % clk $end
$var wire 1 8 d $end
$var wire 1 9 rst $end
$var reg 1 : q $end
$upscope $end
$scope module qa3 $end
$var wire 1 % clk $end
$var wire 1 ; d $end
$var wire 1 < rst $end
$var reg 1 = q $end
$upscope $end
$scope module qa4 $end
$var wire 1 % clk $end
$var wire 1 > d $end
$var wire 1 ? rst $end
$var reg 1 @ q $end
$upscope $end
$scope module qb0 $end
$var wire 1 % clk $end
$var wire 1 A d $end
$var wire 1 B rst $end
$var reg 1 C q $end
$upscope $end
$scope module qb1 $end
$var wire 1 % clk $end
$var wire 1 D d $end
$var wire 1 E rst $end
$var reg 1 F q $end
$upscope $end
$scope module qb2 $end
$var wire 1 % clk $end
$var wire 1 G d $end
$var wire 1 H rst $end
$var reg 1 I q $end
$upscope $end
$scope module qb3 $end
$var wire 1 % clk $end
$var wire 1 J d $end
$var wire 1 K rst $end
$var reg 1 L q $end
$upscope $end
$scope module qb4 $end
$var wire 1 % clk $end
$var wire 1 M d $end
$var wire 1 N rst $end
$var reg 1 O q $end
$upscope $end
$scope module qcin $end
$var wire 1 % clk $end
$var wire 1 P d $end
$var wire 1 Q rst $end
$var reg 1 + q $end
$upscope $end
$scope module qsum0 $end
$var wire 1 % clk $end
$var wire 1 R d $end
$var wire 1 S rst $end
$var reg 1 T q $end
$upscope $end
$scope module qsum1 $end
$var wire 1 % clk $end
$var wire 1 U d $end
$var wire 1 V rst $end
$var reg 1 W q $end
$upscope $end
$scope module qsum2 $end
$var wire 1 % clk $end
$var wire 1 X d $end
$var wire 1 Y rst $end
$var reg 1 Z q $end
$upscope $end
$scope module qsum3 $end
$var wire 1 % clk $end
$var wire 1 [ d $end
$var wire 1 \ rst $end
$var reg 1 ] q $end
$upscope $end
$scope module qsum4 $end
$var wire 1 % clk $end
$var wire 1 ^ d $end
$var wire 1 _ rst $end
$var reg 1 ` q $end
$upscope $end
$upscope $end
$upscope $end
$enddefinitions $end
#0
$dumpvars
x`
z_
x^
x]
z\
x[
xZ
zY
xX
xW
zV
xU
xT
zS
xR
zQ
0P
xO
zN
0M
xL
zK
0J
xI
zH
0G
xF
zE
0D
xC
zB
0A
x@
z?
0>
x=
z<
0;
x:
z9
08
x7
z6
05
x4
z3
02
bx0 1
bx 0
bx /
bx .
bx -
bx ,
x+
bx *
bx )
b1xxxx1xxx1xx1xx (
b0 '
b0 &
0%
b0 $
b0 #
x"
bx !
$end
#50
0^
0U
0X
0[
0"
b0 1
0R
b0 *
b111111111111111 (
b0 0
b0 .
b11111 /
04
07
0:
0=
b0 -
0@
0C
0F
0I
0L
b0 ,
0O
0+
1%
#100
1A
12
0%
b1 $
b1 '
b1 #
b1 &
#150
1U
b10 *
b1 0
b10 1
b11110 /
0`
0]
0Z
0W
b0 !
b0 )
0T
b1 ,
1C
b1 -
14
1%
#200
15
18
1;
1>
0%
b11111 #
b11111 &
#250
1"
b11110 1
0U
0X
0[
0^
b101111011101101 (
b0 *
b11110 .
17
1:
1=
b11111 -
1@
b10 !
b10 )
1W
1%
#300
1G
1J
05
0;
0%
b1101 $
b1101 '
b10101 #
b10101 &
#350
0^
1"
b11010 1
0X
1U
b101 0
b111011110111111 (
b10 *
b11010 /
b11000 .
b0 !
b0 )
0W
1L
b1101 ,
1I
0=
b10101 -
07
1%
#400
1D
0G
1M
02
15
08
0>
0%
b11011 $
b11011 '
b10 #
b10 &
#450
1^
0"
0U
1X
1[
1R
b111111111111111 (
b11101 *
b10 0
b100 1
b11001 .
b11101 /
04
17
0:
b10 -
0@
1F
0I
b11011 ,
1O
b10 !
b10 )
1W
1%
#500
1G
12
18
1;
1>
0%
b11111 $
b11111 '
b11111 #
b11111 &
#550
1U
1^
1"
1[
0R
b11110 *
b11111 0
b11110 1
b0 .
b0 /
1`
1]
1Z
0W
b11101 !
b11101 )
1T
b11111 ,
1I
1@
1=
1:
b11111 -
14
1%
#600
0%
#650
0T
b11110 !
b11110 )
1W
1%
